qiskit_ibm_ai_local_transpiler-0.4.2.dist-info/METADATA
qiskit_ibm_ai_local_transpiler-0.4.2.dist-info/WHEEL
qiskit_ibm_ai_local_transpiler/__init__.py
qiskit_ibm_ai_local_transpiler/clifford/__init__.py
qiskit_ibm_ai_local_transpiler/clifford/inference.py
qiskit_ibm_ai_local_transpiler/clifford/utils.py
qiskit_ibm_ai_local_transpiler/config/config.json
qiskit_ibm_ai_local_transpiler/config/config.py
qiskit_ibm_ai_local_transpiler/linear_function/__init__.py
qiskit_ibm_ai_local_transpiler/linear_function/inference.py
qiskit_ibm_ai_local_transpiler/linear_function/utils.py
qiskit_ibm_ai_local_transpiler/pauli/__init__.py
qiskit_ibm_ai_local_transpiler/pauli/inference.py
qiskit_ibm_ai_local_transpiler/pauli/pauli_network.py
qiskit_ibm_ai_local_transpiler/pauli/utils.py
qiskit_ibm_ai_local_transpiler/permutation/__init__.py
qiskit_ibm_ai_local_transpiler/permutation/inference.py
qiskit_ibm_ai_local_transpiler/permutation/utils.py
qiskit_ibm_ai_local_transpiler/qiskit_ibm_ai_local_transpiler_rs.cpython-39-x86_64-linux-gnu.so
qiskit_ibm_ai_local_transpiler/routing/__init__.py
qiskit_ibm_ai_local_transpiler/routing/inference.py
qiskit_ibm_ai_local_transpiler/utils/layouts.py
qiskit_ibm_ai_local_transpiler/utils/rust_qc_utils.py
qiskit_ibm_ai_local_transpiler/utils/transpile.py
qiskit_ibm_ai_local_transpiler-0.4.2.dist-info/RECORD
