Metadata-Version: 2.4
Name: qiskit-ibm-ai-local-transpiler
Version: 0.4.2
Classifier: Environment :: Console
Classifier: Intended Audience :: Developers
Classifier: Intended Audience :: Science/Research
Classifier: Operating System :: MacOS
Classifier: Operating System :: Microsoft :: Windows
Classifier: Operating System :: POSIX :: Linux
Classifier: Programming Language :: Python :: 3 :: Only
Classifier: Programming Language :: Python :: 3.9
Classifier: Programming Language :: Python :: 3.10
Classifier: Programming Language :: Python :: 3.11
Classifier: Programming Language :: Python :: 3.12
Classifier: Programming Language :: Python :: 3.13
Classifier: Topic :: Scientific/Engineering
Requires-Dist: qiskit>=1.4.2
Requires-Dist: qiskit-ibm-runtime>=0.37.0
Requires-Dist: networkx==2.8.5
Requires-Dist: jsonschema~=4.23
Requires-Dist: pytest>=5.4.0 ; extra == 'testing'
Requires-Dist: pytest-asyncio ; extra == 'testing'
Requires-Dist: black==24.1.0 ; extra == 'testing'
Requires-Dist: black[jupyter]==24.1.0 ; extra == 'testing'
Provides-Extra: testing
Summary: This package allows you to run a local version of the Qiskit AI-powered transpiler passes.
Keywords: qiskit,quantum circuit,quantum computing,AI,AI transpiler,Qiskit AI,quantum,sdk
Author: IBM Quantum
Requires-Python: >=3.9
